[{"precio":"85000","categoria":"mensual","ubicacion":"Kennedy","tipoPropiedad":"Apartaestudio","descripcion":"Hermoso apartamento de 1 habitación y un baño, sala comedor amplia, zona de lavandería, cocina abierta integral, vigilancia 24 horas, cerca a parques, Hospitales, supermercados, centros comerciales y universidades. Excelente ubicación.","habitaciones":"2","qty":"2","baños":"2","ciudad":"Bogotá","area":"75","img":"IMG_4746.jpg","direccion":"Cra 10 # 64 45","titulo":"Excelente Apartamento Chapinero","outstanding":true,"id":"2ghLcaU2Sxg2u9br8EX3","quantity":5},{"baños":"1","area":"55","titulo":"local con terraza Cedritos","precio":"350000","ubicacion":"Cedritos","categoria":"dias","habitaciones":"2","img":"_MG_5679.jpg","id":"T8G94r23yyI42a9jDZVZ","quantity":3}]